README.md
setup.py
plsp/Experimental_Logger.py
plsp/_README.py
plsp/__Color_Configuration.py
plsp/__Debug_Context.py
plsp/__Debug_Mode.py
plsp/__IO_Direction.py
plsp/__Logger.py
plsp/__Shared_Logger.py
plsp/__init__.py
plsp/_pickled.py
plsp/templated_setup.py
plsp.egg-info/PKG-INFO
plsp.egg-info/SOURCES.txt
plsp.egg-info/dependency_links.txt
plsp.egg-info/top_level.txt
plsp/formatters/I_Final_Formatter.py
plsp/formatters/Logging_Segment_Generator.py
plsp/formatters/__init__.py
plsp/formatters/bundled.py