Metadata-Version: 2.1
Name: plsp
Version: 0.261
Summary: A simple, easy to use, and powerful logging library for Python.
Author: matrikater (Joel Watson)
